python_project_beta/__init__.py
python_project_beta/__main__.py
python_project_beta/example.py
python_project_beta-1.0.0.dist-info/AUTHORS.md
python_project_beta-1.0.0.dist-info/LICENCE
python_project_beta-1.0.0.dist-info/METADATA
python_project_beta-1.0.0.dist-info/WHEEL
python_project_beta-1.0.0.dist-info/entry_points.txt
python_project_beta-1.0.0.dist-info/RECORD
