Metadata-Version: 2.3
Name: python-project-beta
Version: 1.0.0
Summary: Awesome `python-project-beta` is a Python cli/package created with https://gitlab.com/manoelpqueiroz/galactipy
Home-page: https://github.com/manoelpqueiroz/python-project-beta
License: MIT
Author: Manoel Pereira de Queiroz
Author-email: contact@manoelpqueiroz.com
Requires-Python: >=3.9,<4.0
Classifier: Development Status :: 3 - Alpha
Classifier: Intended Audience :: Developers
Classifier: License :: OSI Approved :: MIT License
Classifier: Operating System :: OS Independent
Classifier: Programming Language :: Python :: 3
Classifier: Programming Language :: Python :: 3.9
Classifier: Programming Language :: Python :: 3.10
Classifier: Programming Language :: Python :: 3.11
Classifier: Programming Language :: Python :: 3.12
Classifier: Programming Language :: Python :: 3.13
Classifier: Topic :: Software Development :: Libraries :: Python Modules
Requires-Dist: rich (>=12.6.0,<13.0.0)
Requires-Dist: typer[all] (>=0.7.0,<0.8.0)
Project-URL: Repository, https://github.com/manoelpqueiroz/python-project-beta
